{"name":"大数据","slug":"大数据","count":1,"postlist":[{"title":"elasticSearch笔记","uid":"bed96b130d460c27974096119f84e9f1","slug":"ElasticSearch笔记","date":"2022-04-06T17:26:08.000Z","updated":"2022-04-06T17:27:18.000Z","comments":true,"path":"api/articles/ElasticSearch笔记.json","keywords":null,"cover":"https://img1.baidu.com/it/u=3636892071,3340316976&fm=253&fmt=auto&app=138&f=JPEG?w=980&h=300","text":"ElasticSearch顶尖高手系列——基础课程 大数据技术栈：Haddop、spark、storm、hive、hbase、zookeeper、elasticsearch 核心知识篇课程特点： 使用了elasticsearch5.2版本进行讲解，市面上的书籍和视频几乎都停留在2...","link":"","photos":[],"count_time":{"symbolsCount":"54k","symbolsTime":"49 mins."},"categories":[{"name":"大数据","slug":"大数据","count":1,"path":"api/categories/大数据.json"}],"tags":[{"name":"elasticSearch","slug":"elasticSearch","count":1,"path":"api/tags/elasticSearch.json"}],"author":{"name":"zhiQiang","slug":"blog-author","avatar":"https://img-blog.csdnimg.cn/20210313122054101.png","link":"/","description":"有情有颜有才缺钱","socials":{"github":"https://github.com/Viserion-nlper","twitter":"","stackoverflow":"","wechat":"","qq":"","weibo":"https://weibo.com/u/7318914058","zhihu":"https://www.zhihu.com/people/tridiamond","csdn":"https://blog.csdn.net/TriDiamond6","juejin":"https://juejin.cn/user/1873223546578589","customs":{"bilibili":{"icon":"/img/touxiang.jpg","link":"https://live.bilibili.com/22619211"},"baidu":{"icon":"iconfont icon-baidu","link":"https://live.bilibili.com/22619211"},"facebook":{"icon":"/svg/facebook.svg","link":"https://live.bilibili.com/22619211"}}}},"feature":true}]}